LICENSE
README.md
setup.py
domain_expire/__init__.py
domain_expire.egg-info/PKG-INFO
domain_expire.egg-info/SOURCES.txt
domain_expire.egg-info/dependency_links.txt
domain_expire.egg-info/requires.txt
domain_expire.egg-info/top_level.txt