Metadata-Version: 2.1
Name: domain-expire
Version: 0.0.1
Summary: check domain near expire date
Home-page: https://github.com/ipconfiger/domain-expire
Author: Alexander.Li
Author-email: superpowerlee@gmaial.com
License: UNKNOWN
Platform: UNKNOWN
License-File: LICENSE
